QASchedule/__init__.py
QASchedule-1.0.dist-info/LICENSE
QASchedule-1.0.dist-info/METADATA
QASchedule-1.0.dist-info/WHEEL
QASchedule-1.0.dist-info/top_level.txt
QASchedule-1.0.dist-info/zip-safe
QASchedule-1.0.dist-info/RECORD
