Metadata-Version: 2.1
Name: QASchedule
Version: 1.0
Summary: QUANTAXIS REALTIME: QUANTAXIS REALTIME RESOLUTION
Home-page: https://github.com/yutiansut/qaschedule
Author: yutiansut
Author-email: yutiansut@qq.com
License: MIT
Keywords: quantaxis,quant,finance,Backtest,Framework
Platform: UNKNOWN
Classifier: License :: OSI Approved :: MIT License
Classifier: Programming Language :: Python
Classifier: Intended Audience :: Developers
Classifier: Operating System :: OS Independent
Requires-Dist: pika
Requires-Dist: quantaxis (>=1.1.10.dev2)
